aiomoex/__init__.py
aiomoex/candles.py
aiomoex/client.py
aiomoex/history.py
aiomoex/py.typed
aiomoex/reference.py
aiomoex/request_helpers.py
aiomoex/statistics.py
aiomoex-2.2.0.dist-info/METADATA
aiomoex-2.2.0.dist-info/WHEEL
aiomoex-2.2.0.dist-info/licenses/LICENSE
aiomoex-2.2.0.dist-info/RECORD
