Metadata-Version: 2.4
Name: aiomoex
Version: 2.2.0
Summary: Asyncio MOEX ISS API
Author-email: Mikhail Korotkov aka WLMike <wlmike@gmail.com>
License: http://unlicense.org
License-File: LICENSE
Requires-Python: >=3.13
Requires-Dist: aiohttp>=3.12.0
